{
  "date": "2026-06-13",
  "generated_at": "2026-06-13T15:01:21.219449-04:00",
  "pick_count": 7,
  "picks": [
    {
      "id": 2580,
      "hash": "70a271fe6964cb662b3d5ad3a8d740dc3633aa11a9d0819a14eeb0bfc43f645b",
      "league": "NBA",
      "market_type": "spread",
      "pick_text": "Knicks -5.5",
      "created_at": "2026-06-11T10:40:11.638107+00:00"
    },
    {
      "id": 2581,
      "hash": "70cad68e5bc470d974031364c7659a7bae35b402276d693b060f942b6cf604e6",
      "league": "NBA",
      "market_type": "total",
      "pick_text": "Under 216.5",
      "created_at": "2026-06-11T10:40:11.638107+00:00"
    },
    {
      "id": 2612,
      "hash": "e77b9dfa663d8ba2b60ea9ca4bdb4ccf75eeafeec620db6d7f52ec5ec547bdc7",
      "league": "NBA",
      "market_type": "player_prop",
      "pick_text": "Josh Hart Over 4.5 Assists",
      "created_at": "2026-06-13 11:34:08"
    },
    {
      "id": 2614,
      "hash": "ebc9499dc6aff04c74395877888ee6e7bcbc4e62323c9554a3449a4626a4f619",
      "league": "NBA",
      "market_type": "player_prop",
      "pick_text": "Victor Wembanyama Over 11.5 Rebounds",
      "created_at": "2026-06-13 11:34:08"
    },
    {
      "id": 2618,
      "hash": "004597279ec283be22aba253cd4ac6cb1b2afb12471f7d620fc8f9b2cc97193e",
      "league": "MLB",
      "market_type": "moneyline",
      "pick_text": "Los Angeles Angels",
      "created_at": "2026-06-13 15:01:03"
    },
    {
      "id": 2622,
      "hash": "45f715dd8228bca09cdf6cf74f89ca21fc90e49235a273dc9bff974b20016c2c",
      "league": "PARLAY",
      "market_type": "parlay",
      "pick_text": "2-Leg Parlay: Los Angeles Angels + New York Knicks @ San Antonio Spurs Under 216.5",
      "created_at": "2026-06-13 16:01:28"
    },
    {
      "id": 2624,
      "hash": "4adb3078c2c5ce5a26d05af2865bdc6a9ba4efbaabadbf2756d4b981f885bd98",
      "league": "MLB",
      "market_type": "total",
      "pick_text": "Under 7.5",
      "created_at": "2026-06-13 17:01:08"
    }
  ]
}